<?xml version="1.0" encoding="UTF-8"?>
<games>
	<game id="-1" name="Unknown Game" />
	<game id="2" name="America's Army: Special Forces" />
	<game id="3" name="Unreal Tournament" />
	<game id="4" name="Unreal Tournament 2003" />
	<game id="5" name="Counter-Strike 1.6" />
	<game id="32" name="TeamSpeak" />
	<game id="33" name="Ventrilo" />
	<game id="34" name="Mumble" />
	<game id="4096" name="The Temple of Elemental Evil" />
	<game id="4097" name="Wolfenstein: Enemy Territory" />
	<game id="4098" name="Dark Age of Camelot" />
	<game id="4099" name="Dark Age of Camelot - Shrouded Isles" />
	<game id="4100" name="Dungeon Siege" />
	<game id="4284" name="StarCraft Brood War" />
	<game id="4101" name="StarCraft" />
	<game id="4285" name="Diablo II - Lord of Destruction" />
	<game id="4102" name="Diablo II" />
	<game id="4103" name="XEvil" />
	<game id="4104" name="Meridian 59" />
	<game id="4105" name="Battlefield 1942" />
	<game id="4106" name="Everquest" />
	<game id="4107" name="Halo" />
	<game id="4108" name="Neverwinter Nights" />
	<game id="4109" name="Star Wars Galaxies: An Empire Divided" />
	<game id="4110" name="PlanetSide" />
	<game id="4111" name="Quake III Arena" />
	<game id="4112" name="Warcraft III" />
	<game id="4113" name="Lineage" />
	<game id="4114" name="Medal of Honor Allied Assault" />
	<game id="4115" name="Diablo" />
	<game id="4116" name="Quake II" />
	<game id="4117" name="Legends of Mir II" />
	<game id="4118" name="Final Fantasy XI Online" />
	<game id="4119" name="Call of Duty Single Player" />
	<game id="4120" name="Call of Duty Multiplayer" />
	<game id="4121" name="Star Wars Knights of the Old Republic" />
	<game id="4122" name="Need For Speed: Underground" />
	<game id="4123" name="RollerCoaster Tycoon 2" />
	<game id="4124" name="Age of Empires II" />
	<game id="4125" name="Savage: The Battle for Newerth" />
	<game id="4126" name="Civilization III" />
	<game id="4127" name="SimCity 4" />
	<game id="4128" name="C&amp;C Red Alert 2" />
	<game id="4129" name="C&amp;C Generals" />
	<game id="4130" name="Gunbound" />
	<game id="4131" name="Fallout Tactics" />
	<game id="4132" name="Age of Wonders: Shadow Magic" />
	<game id="4133" name="Warlords IV: Heroes of Etheria" />
	<game id="4134" name="PartyPoker.com" />
	<game id="4135" name="Rise of Nations" />
	<game id="4136" name="Tribes 2" />
	<game id="4137" name="Unreal II XMP" />
	<game id="4138" name="Unreal II: The Awakening SP" />
	<game id="4139" name="Age of Mythology" />
	<game id="4140" name="Age of Mythology - The Titans Expansion" />
	<game id="4141" name="Raven Shield" />
	<game id="4142" name="Madden NFL 2004" />
	<game id="4143" name="Tiger Woods PGA Tour 2004" />
	<game id="4144" name="Civilization III Conquests" />
	<game id="4145" name="Civilization III Play the World" />
	<game id="4146" name="FIFA 2003" />
	<game id="4147" name="Spider Solitaire" />
	<game id="4148" name="Solitaire" />
	<game id="4149" name="Minesweeper" />
	<game id="4150" name="Medal of Honor Allied Assault - Breakthrough" />
	<game id="4151" name="Soldier of Fortune II Multiplayer" />
	<game id="4152" name="Medal of Honor Allied Assault - Spearhead" />
	<game id="4153" name="Soldier of Fortune II Single Player" />
	<game id="4154" name="Ghost Recon" />
	<game id="4155" name="Delta Force Black Hawk Down" />
	<game id="4156" name="C&amp;C Generals - Zero Hour" />
	<game id="4157" name="Jedi Academy Single Player" />
	<game id="4158" name="Jedi Academy Multiplayer" />
	<game id="4159" name="Silent Storm" />
	<game id="4160" name="Jedi Knight II Multiplayer" />
	<game id="4161" name="Jedi Knight II Single Player" />
	<game id="4162" name="Unreal Tournament 2004 Demo" />
	<game id="4163" name="Savage: The Battle for Newerth DEMO 2.0" />
	<game id="4164" name="Natural Selection" />
	<game id="4165" name="Day of Defeat 1.3" />
	<game id="4166" name="Deathmatch Classic (Steam)" />
	<game id="4167" name="Half-Life (Steam)" />
	<game id="4168" name="Opposing Force (Steam)" />
	<game id="4169" name="Ricochet (Steam)" />
	<game id="4170" name="Team Fortress Classic (Steam)" />
	<game id="4171" name="Vietcong" />
	<game id="4172" name="Aliens vs. Predator 2" />
	<game id="4173" name="Return to Castle Wolfenstein Single Player" />
	<game id="4174" name="Return to Castle Wolfenstein Multiplayer" />
	<game id="4175" name="Dark Age of Camelot - Trials of Atlantis" />
	<game id="4176" name="Tron 2.0" />
	<game id="4177" name="Red Faction II" />
	<game id="4178" name="C&amp;C Renegade" />
	<game id="4179" name="Second Life" />
	<game id="4180" name="Far Cry" />
	<game id="4181" name="Unreal Tournament 2004" />
	<game id="4182" name="Battlefield Vietnam" />
	<game id="4183" name="Soldat" />
	<game id="4184" name="Combat Flight Simulator 3" />
	<game id="4185" name="Midnight Club 2" />
	<game id="4186" name="Counter-Strike 1.5" />
	<game id="4187" name="Counter-Strike: Condition Zero" />
	<game id="4188" name="Carom 3D" />
	<game id="4189" name="The Specialists" />
	<game id="4190" name="Star Trek Elite Force II" />
	<game id="4191" name="NetGammon" />
	<game id="4192" name="Empire Earth" />
	<game id="4193" name="Condition Zero: Deleted Scenes" />
	<game id="4194" name="Splinter Cell Pandora Tomorrow Single Player" />
	<game id="4195" name="Splinter Cell Pandora Tomorrow Multiplayer" />
	<game id="4196" name="Chrome MP Demo 2004" />
	<game id="4197" name="Ragnarok Online" />
	<game id="4198" name="Breed" />
	<game id="4393" name="Painkiller Battle out of Hell" />
	<game id="4199" name="Painkiller" />
	<game id="4200" name="Chrome" />
	<game id="4201" name="Lock On" />
	<game id="4202" name="Sacred" />
	<game id="4203" name="Tactical Ops" />
	<game id="4204" name="Starsiege Tribes" />
	<game id="4205" name="NASCAR Racing 3" />
	<game id="4206" name="NASCAR Racing 4" />
	<game id="4207" name="NASCAR Racing 2003 Season" />
	<game id="4208" name="Star Trek Voyager: Elite Force Multiplayer" />
	<game id="4209" name="Star Trek Armada" />
	<game id="4210" name="Universal Combat Single Player" />
	<game id="4211" name="Universal Combat Multiplayer" />
	<game id="4212" name="Operation Flashpoint" />
	<game id="4213" name="Operation Flashpoint Resistance" />
	<game id="4214" name="IL-2 Sturmovik Collection" />
	<game id="4215" name="Lineage II" />
	<game id="4216" name="World of Warcraft" />
	<game id="4217" name="City of Heroes" />
	<game id="4218" name="Rise of Nations - Thrones &amp; Patriots" />
	<game id="4219" name="Manhunt" />
	<game id="4220" name="Hitman 2 - Silent Assassin" />
	<game id="4221" name="Hitman Contracts" />
	<game id="4222" name="Iron Storm" />
	<game id="4223" name="Rogue Spear" />
	<game id="4224" name="Rogue Spear - Urban Operations" />
	<game id="4225" name="Star Trek Voyager: Elite Force Single Player" />
	<game id="4226" name="Asheron's Call 2" />
	<game id="4227" name="Legends of Mir III" />
	<game id="4228" name="JX Online" />
	<game id="4229" name="Karma Online" />
	<game id="4230" name="Legends of Mir" />
	<game id="4231" name="Mu Online" />
	<game id="4232" name="Prince of Qin Online" />
	<game id="4233" name="The World of Legend" />
	<game id="4234" name="Soldner Beta Demo" />
	<game id="4235" name="GLQuake" />
	<game id="4236" name="QuakeWorld" />
	<game id="4237" name="There" />
	<game id="4238" name="Red Faction" />
	<game id="4239" name="Halo Custom Edition" />
	<game id="4240" name="Freelancer" />
	<game id="4241" name="Deus Ex" />
	<game id="4242" name="True Crime - Streets of LA" />
	<game id="4243" name="The Saga of Ryzom" />
	<game id="4244" name="Shadowbane" />
	<game id="4245" name="MechWarrior 4 Vengeance" />
	<game id="4246" name="MechWarrior Mercenaries" />
	<game id="4247" name="Serious Sam - The Second Encounter" />
	<game id="4248" name="Joint Operations: Typhoon Rising" />
	<game id="4249" name="Thief - Deadly Shadows" />
	<game id="4250" name="Rune" />
	<game id="4251" name="GetAmped" />
	<game id="4252" name="Mabinogi" />
	<game id="4253" name="Priston Tale" />
	<game id="4254" name="Horizons Online" />
	<game id="4255" name="Ultima Online" />
	<game id="4256" name="Hidden &amp; Dangerous" />
	<game id="4257" name="Hidden &amp; Dangerous 2" />
	<game id="4258" name="C&amp;C Yuri's Revenge" />
	<game id="4259" name="Empires Dawn of the Modern World" />
	<game id="4260" name="Medieval - Total War" />
	<game id="4261" name="Soldner - Secret Wars" />
	<game id="4262" name="A3" />
	<game id="4263" name="John Deere American Farmer" />
	<game id="4264" name="MapleStory" />
	<game id="4265" name="GunZ: The Duel" />
	<game id="4266" name="Grand Theft Auto III" />
	<game id="4267" name="Grand Theft Auto: Vice City" />
	<game id="4268" name="MameUI" />
	<game id="4269" name="Tony Hawk's Pro Skater 3" />
	<game id="4270" name="Warcraft III - The Frozen Throne" />
	<game id="4271" name="Doom 3" />
	<game id="4272" name="Tony Hawk's Pro Skater 4" />
	<game id="4273" name="Toca Race Driver 2" />
	<game id="4274" name="Vietcong Fist Alpha" />
	<game id="4275" name="Rainbow Six 3 - Athena Sword" />
	<game id="4276" name="Half-Life 1.5" />
	<game id="4277" name="Day of Defeat 1.5" />
	<game id="4278" name="Team Fortress Classic 1.5" />
	<game id="4279" name="Opposing Force 1.5" />
	<game id="4280" name="Deathmatch Classic 1.5" />
	<game id="4281" name="Ricochet 1.5" />
	<game id="4282" name="Red Orchestra" />
	<game id="4283" name="Ground Control II" />
	<game id="4286" name="Take-Out Weight Curling" />
	<game id="4287" name="Take-Out Weight Curling 2" />
	<game id="4288" name="Delta Force" />
	<game id="4289" name="Delta Force 2" />
	<game id="4290" name="XIII" />
	<game id="4291" name="SpellForce - The Order of Dawn" />
	<game id="4292" name="Gore - Ultimate Soldier" />
	<game id="4293" name="The Sims" />
	<game id="4294" name="Max Payne 2" />
	<game id="4295" name="Codename Gordon" />
	<game id="4296" name="Earth's Special Forces" />
	<game id="4297" name="Digital Paintball" />
	<game id="4298" name="Firearms" />
	<game id="4299" name="Sven Co-op" />
	<game id="4300" name="Warhammer 40,000 Dawn of War Beta" />
	<game id="4301" name="Frag Ops" />
	<game id="4302" name="Troopers: Dawn of Destiny" />
	<game id="4303" name="Counter-Strike: Source (Beta)" />
	<game id="4304" name="Medal of Honor Pacific Assault" />
	<game id="4305" name="No One Lives Forever 2" />
	<game id="4306" name="4x4 Evolution" />
	<game id="4307" name="Max Payne" />
	<game id="4308" name="SimCity 3000 Unlimited" />
	<game id="4309" name="The Lord of the Rings - The Battle for Middle-Earth" />
	<game id="4310" name="Call of Duty United Offensive Single Player" />
	<game id="4311" name="Call of Duty United Offensive Multiplayer" />
	<game id="4312" name="The Elder Scrolls III: Morrowind" />
	<game id="4313" name="Warlords Battlecry III" />
	<game id="4314" name="Colin Mcrae Rally 04" />
	<game id="4315" name="MotoGP 2" />
	<game id="4316" name="Unreal" />
	<game id="4317" name="Nox" />
	<game id="4318" name="Total Annihilation Kingdoms" />
	<game id="4319" name="Tribes Vengeance Multiplayer Demo" />
	<game id="4320" name="Eve Online" />
	<game id="4321" name="EverQuest II Beta" />
	<game id="4322" name="The Sims 2" />
	<game id="4323" name="Star Wars Battlefront" />
	<game id="4324" name="Dawn of War" />
	<game id="4325" name="Rome - Total War" />
	<game id="4326" name="Call of Duty United Offensive Single Player Demo" />
	<game id="4327" name="Anarchy Online" />
	<game id="4328" name="Full Spectrum Warrior" />
	<game id="4329" name="Kohan II Kings of War" />
	<game id="4330" name="Tribes Vengeance" />
	<game id="4331" name="Counter-Strike: Source" />
	<game id="4332" name="Star Wars Galaxies - The Jump to Lightspeed Beta" />
	<game id="4333" name="Gotcha!" />
	<game id="4334" name="Leisure Suit Larry - Magna Cum Laude" />
	<game id="4335" name="Stepmania CVS" />
	<game id="4336" name="Trackmania" />
	<game id="4337" name="Tony Hawk's Underground 2" />
	<game id="4338" name="Dawn of War Demo" />
	<game id="4339" name="Men of Valor MP Demo" />
	<game id="4340" name="Madden NFL 2005" />
	<game id="4341" name="Tiger Woods PGA Tour 2005" />
	<game id="4342" name="NHL 2005" />
	<game id="4343" name="Evil Genius" />
	<game id="4621" name="RollerCoaster Tycoon 3 Soaked" />
	<game id="4344" name="RollerCoaster Tycoon 3" />
	<game id="4345" name="Guild Wars" />
	<game id="4346" name="Medal of Honor Pacific Assault MP Demo" />
	<game id="4347" name="Axis &amp; Allies" />
	<game id="4348" name="The Simpsons Hit &amp; Run" />
	<game id="4349" name="ShellShock Nam67" />
	<game id="4350" name="Deus Ex Invisible War" />
	<game id="4351" name="Kingpin Life of Crime" />
	<game id="4352" name="EverQuest II" />
	<game id="4353" name="Need for Speed: Underground 2" />
	<game id="4354" name="FIFA Soccer 2005" />
	<game id="4355" name="NBA Live 2005" />
	<game id="4356" name="Flight Simulator 2004" />
	<game id="4357" name="Half-Life 2" />
	<game id="4358" name="Half-Life: Source" />
	<game id="4359" name="Sid Meier's Pirates!" />
	<game id="4360" name="Joint Operations: Escalation" />
	<game id="4361" name="Hidden &amp; Dangerous 2 Sabre Squadron" />
	<game id="4362" name="Vampire - The Masquerade Bloodlines" />
	<game id="4363" name="Half-Life 2: Deathmatch" />
	<game id="5457" name="Zoo Tycoon 2: Extinct Animals" />
	<game id="4933" name="Zoo Tycoon 2: Marine Mania" />
	<game id="4839" name="Zoo Tycoon 2 African Adventure" />
	<game id="4704" name="Zoo Tycoon 2: Endangered Species" />
	<game id="4364" name="Zoo Tycoon 2" />
	<game id="4365" name="Prince of Persia Warrior Within" />
	<game id="4366" name="Men of Valor" />
	<game id="4367" name="Worms 3D" />
	<game id="4368" name="The Chronicles of Riddick: Escape from Butcher Bay" />
	<game id="4369" name="System Shock 2" />
	<game id="4370" name="Armed and Dangerous" />
	<game id="4371" name="Armies of Exigo" />
	<game id="4372" name="Codename: Panzers, Phase 1" />
	<game id="4373" name="Dungeon Siege Legends of Aranna" />
	<game id="4374" name="SAS Into the Lion's Den" />
	<game id="4375" name="Action Unreal Tournament 2004" />
	<game id="4376" name="Age of Empires II: The Conquerors Expansion" />
	<game id="4377" name="Kill.Switch" />
	<game id="4378" name="Soldier of Fortune" />
	<game id="4379" name="Risk Your Life" />
	<game id="4380" name="Jedi Knight" />
	<game id="4381" name="No One Lives Forever" />
	<game id="4636" name="C&amp;C Tiberian Sun Firestorm" />
	<game id="4382" name="C&amp;C Tiberian Sun" />
	<game id="4383" name="Knight Online" />
	<game id="4384" name="Star Wars Galactic Battlegrounds" />
	<game id="4385" name="Star Wars Galactic Battlegrounds - Clone Campaigns" />
	<game id="4386" name="Star Wars Knights of the Old Republic II: The Sith Lords" />
	<game id="4387" name="Armies of Exigo Single Player Demo" />
	<game id="4388" name="Homeworld" />
	<game id="4389" name="Homeworld 2" />
	<game id="4390" name="Warcraft II" />
	<game id="4391" name="Wulfram 2" />
	<game id="4392" name="ProQuake" />
	<game id="4394" name="R.O.S.E. Online Evolution" />
	<game id="4395" name="Dark Age of Camelot - Catacombs" />
	<game id="4396" name="Splinter Cell Chaos Theory Versus Beta" />
	<game id="4397" name="Worms Armageddon" />
	<game id="4398" name="Battlefield 2 Demo" />
	<game id="4399" name="Star Wars Republic Commando Demo" />
	<game id="4400" name="The Punisher" />
	<game id="4401" name="Postal 2 Share the Pain" />
	<game id="4402" name="SWAT 4 MP Beta" />
	<game id="4403" name="Winning Eleven 7 INTERNATIONAL" />
	<game id="4404" name="The Settlers: Heritage of Kings Demo" />
	<game id="4405" name="City of Heroes EU" />
	<game id="4406" name="Hearts of Iron II" />
	<game id="4407" name="R.Y.L. Path of the Emperor" />
	<game id="4408" name="Splinter Cell Chaos Theory Single Player Demo" />
	<game id="4409" name="4x4 Evo2" />
	<game id="4410" name="Star Wars Republic Commando" />
	<game id="4411" name="The Sims 2 University" />
	<game id="4412" name="Freedom Force vs The 3rd Reich" />
	<game id="4413" name="Black &amp; White" />
	<game id="4414" name="The Matrix Online" />
	<game id="4415" name="NASCAR SimRacing" />
	<game id="4416" name="Brothers in Arms" />
	<game id="4417" name="FlatOut" />
	<game id="4418" name="Silent Hunter III" />
	<game id="4419" name="Nexus - The Jupiter Incident" />
	<game id="4420" name="Act of War: Direct Action" />
	<game id="4421" name="Prince of Persia - The Sands of Time" />
	<game id="4422" name="Colin Mcrae Rally 05" />
	<game id="4423" name="Playboy - The Mansion" />
	<game id="4424" name="Splinter Cell Chaos Theory Single Player" />
	<game id="4425" name="Splinter Cell Chaos Theory Multiplayer" />
	<game id="4426" name="Giants: Citizen Kabuto" />
	<game id="4427" name="Icewind Dale" />
	<game id="4428" name="Icewind Dale - Heart of Winter" />
	<game id="4429" name="Doom 3 Resurrection of Evil" />
	<game id="4430" name="Darwinia Demo" />
	<game id="4431" name="Darwinia" />
	<game id="4432" name="SWAT 4" />
	<game id="4433" name="Worms World Party" />
	<game id="4434" name="Driv3r" />
	<game id="4435" name="Gaming Club Poker" />
	<game id="4436" name="Winning Eleven 8" />
	<game id="4437" name="Tropico" />
	<game id="4438" name="Tropico 2 Pirate Cove" />
	<game id="4439" name="Kal Online" />
	<game id="4440" name="Project Snowblind Single Player" />
	<game id="4441" name="Splinter Cell" />
	<game id="4442" name="Grand Theft Auto 2" />
	<game id="4443" name="Caesar 3" />
	<game id="4444" name="Pharaoh" />
	<game id="4445" name="Lego Star Wars" />
	<game id="4446" name="Close Combat First to Fight" />
	<game id="4447" name="Empire Earth II" />
	<game id="4448" name="Stronghold 2" />
	<game id="4449" name="The Settlers: Heritage of Kings" />
	<game id="4450" name="Delta Force Xtreme" />
	<game id="4451" name="StillLife" />
	<game id="4452" name="Dungeon Siege II Demo" />
	<game id="4553" name="Psychonauts" />
	<game id="4554" name="GTR" />
	<game id="4555" name="Pariah" />
	<game id="4556" name="Psychotoxic" />
	<game id="4557" name="Immortal Cities: Children of The Nile" />
	<game id="4558" name="Championship Manager 5" />
	<game id="4559" name="Football Manager 2005" />
	<game id="4560" name="Total Club Manager 2005" />
	<game id="4561" name="Soldiers - Heroes of World War II" />
	<game id="4562" name="Plan of Attack" />
	<game id="4563" name="Total Annihilation" />
	<game id="4564" name="Pro Evolution Soccer 4" />
	<game id="4565" name="Age of Empires" />
	<game id="4566" name="Trackmania Sunrise" />
	<game id="4567" name="PokerStars.com" />
	<game id="4568" name="PokerRoom.com" />
	<game id="4569" name="EmpirePoker.com" />
	<game id="4570" name="TruePoker.com" />
	<game id="4571" name="Project Snowblind Multiplayer" />
	<game id="4572" name="Grand Theft Auto: San Andreas" />
	<game id="4573" name="Cossacks II" />
	<game id="4574" name="Serious Sam" />
	<game id="4575" name="Universal Combat AWA Single Player" />
	<game id="4576" name="Universal Combat AWA Multiplayer" />
	<game id="4577" name="Imperial Glory" />
	<game id="4578" name="Battlefield 2" />
	<game id="4579" name="18 Wheels of Steel Pedal to the Metal" />
	<game id="4580" name="Area 51" />
	<game id="4581" name="Universal Combat Gold Single Player" />
	<game id="4582" name="Universal Combat Gold Multiplayer" />
	<game id="4583" name="Mojo Master" />
	<game id="4584" name="Juiced" />
	<game id="4585" name="Zoo Tycoon" />
	<game id="4586" name="Need for Speed II SE" />
	<game id="4587" name="Need for Speed: High Stakes" />
	<game id="4588" name="Need for Speed III: Hot Pursuit" />
	<game id="4589" name="Need for Speed: Porsche Unleashed" />
	<game id="4590" name="Need for Speed: Hot Pursuit 2" />
	<game id="4591" name="Half-Life 2: Capture the Flag" />
	<game id="4592" name="Half-Life 2: Substance" />
	<game id="4593" name="Garry's Mod" />
	<game id="4594" name="CounterStrike 2D" />
	<game id="4595" name="Continuum" />
	<game id="4596" name="Mafia" />
	<game id="4597" name="Cold Fear" />
	<game id="4598" name="COR" />
	<game id="4599" name="Silent Hill 2" />
	<game id="4600" name="Silent Hill 3" />
	<game id="4601" name="Silent Hill 4" />
	<game id="4602" name="Baldur's Gate" />
	<game id="4603" name="X-Wing vs. TIE Fighter" />
	<game id="4604" name="Stronghold" />
	<game id="4605" name="Stronghold Crusader" />
	<game id="4606" name="Gothic II" />
	<game id="4607" name="The Sims Online" />
	<game id="4608" name="Magic Online" />
	<game id="4609" name="Thief" />
	<game id="4610" name="Thief 2 The Metal Age" />
	<game id="4611" name="Live for Speed" />
	<game id="4612" name="Spartan" />
	<game id="4613" name="Gates of Troy" />
	<game id="4614" name="Age of Empires: The Rise of Rome" />
	<game id="4615" name="Sudden Strike II" />
	<game id="4616" name="Scrapland" />
	<game id="4617" name="Mortyr 2" />
	<game id="4618" name="Homeworld Cataclysm" />
	<game id="4619" name="Fate" />
	<game id="4620" name="Dungeon Siege II" />
	<game id="4622" name="Blue Shift" />
	<game id="4623" name="Control Monger" />
	<game id="4624" name="FEAR SP Demo" />
	<game id="4625" name="Madden NFL 2006" />
	<game id="4626" name="The Bard's Tale" />
	<game id="4627" name="Half-Life: Blue Shift (Steam)" />
	<game id="4628" name="Legion Arena" />
	<game id="4629" name="NTE" />
	<game id="4630" name="Grim Fandango" />
	<game id="4631" name="1602 A.D." />
	<game id="4632" name="Conquer Online" />
	<game id="4633" name="Age of Empires III Trial" />
	<game id="4634" name="Dystopia v1" />
	<game id="4635" name="Toontown Online" />
	<game id="4637" name="Serious Sam 2 Demo" />
	<game id="4638" name="Fallout" />
	<game id="4639" name="Fallout 2" />
	<game id="4640" name="Superpower 2" />
	<game id="4641" name="Enter the Matrix" />
	<game id="4642" name="Rollercoaster Tycoon" />
	<game id="4643" name="Railroad Tycoon 3" />
	<game id="4644" name="Codename: Panzers, Phase 2" />
	<game id="4645" name="Blitzkrieg" />
	<game id="4646" name="NHL 06" />
	<game id="4647" name="MVP Baseball 2005" />
	<game id="4648" name="Fable - The Lost Chapters" />
	<game id="4649" name="Dawn of War Winter Assault" />
	<game id="4650" name="Beats of Rage" />
	<game id="4651" name="Tiger Woods PGA Tour 06" />
	<game id="4652" name="The Sims 2 Nightlife" />
	<game id="4653" name="Day of Defeat: Source" />
	<game id="4654" name="Sacred Underworld" />
	<game id="4655" name="Star Wars Battlefront II" />
	<game id="4656" name="Call of Duty 2 Single Player Demo" />
	<game id="4657" name="Brothers in Arms EIB Demo" />
	<game id="4658" name="FEAR Multiplayer Demo" />
	<game id="4659" name="Rome - Barbarian Invasion" />
	<game id="4660" name="Dragonshard" />
	<game id="4661" name="Brothers in Arms EIB" />
	<game id="4662" name="Serious Sam 2" />
	<game id="4663" name="Black &amp; White 2" />
	<game id="4664" name="FIFA Soccer 06" />
	<game id="4665" name="NBA Live 06" />
	<game id="4666" name="Rag Doll Kung Fu" />
	<game id="4667" name="FEAR Single Player" />
	<game id="4668" name="MotoGP URT 3" />
	<game id="4669" name="Ultimate Spider-Man" />
	<game id="4670" name="X-Men Legends 2" />
	<game id="4671" name="Blitzkrieg 2" />
	<game id="4672" name="18 Wheels of Steel Convoy" />
	<game id="4673" name="Gangland" />
	<game id="4674" name="Risk II" />
	<game id="4675" name="Bet on Soldier" />
	<game id="4676" name="Descent FreeSpace" />
	<game id="4677" name="Prison Tycoon" />
	<game id="4678" name="Quake 4" />
	<game id="4679" name="Age of Empires III" />
	<game id="4680" name="Richard Burns Rally" />
	<game id="4681" name="Indigo Prophecy" />
	<game id="4682" name="Vietcong 2" />
	<game id="4683" name="Call of Duty 2 Single Player" />
	<game id="4684" name="Call of Duty 2 Multiplayer" />
	<game id="4685" name="Civilization IV" />
	<game id="4686" name="LOTR Return of the King" />
	<game id="4687" name="City of Villains" />
	<game id="4688" name="Heroes of the Pacific" />
	<game id="4689" name="Fahrenheit" />
	<game id="4690" name="City of Villains EU" />
	<game id="4691" name="Shattered Union" />
	<game id="4692" name="X2 - The Threat" />
	<game id="4693" name="RollerCoaster Tycoon 3 Wild" />
	<game id="4694" name="Half-Life 2: Lost Coast" />
	<game id="4695" name="Gun" />
	<game id="4696" name="The Movies" />
	<game id="4697" name="The Matrix - The Path of Neo" />
	<game id="4698" name="Contract JACK" />
	<game id="4699" name="BloodRayne" />
	<game id="4700" name="BloodRayne 2" />
	<game id="4701" name="Sourceforts" />
	<game id="4702" name="Need for Speed: Most Wanted" />
	<game id="4703" name="John Deere North American Farmer" />
	<game id="4705" name="Worms 4 Mayhem" />
	<game id="4706" name="Earth 2160" />
	<game id="4707" name="Sniper Elite" />
	<game id="4708" name="Peter Jackson's King Kong" />
	<game id="4709" name="Crime Life" />
	<game id="4710" name="Empire Earth II Art of Supremacy" />
	<game id="4711" name="Quake 4 Demo" />
	<game id="4712" name="Silkroad Online" />
	<game id="4713" name="Flyff" />
	<game id="4714" name="Prince of Persia The Two Thrones" />
	<game id="4715" name="WarRock" />
	<game id="4716" name="X3 - The Reunion" />
	<game id="4717" name="Stubbs the Zombie" />
	<game id="4718" name="Pro Evolution Soccer 5" />
	<game id="4719" name="Football Manager 2006" />
	<game id="4720" name="Star Trek Bridge Commander" />
	<game id="4721" name="Advent Rising" />
	<game id="4722" name="UFO Aftershock" />
	<game id="4723" name="NavyField" />
	<game id="4724" name="Rubies of Eventide" />
	<game id="4725" name="FIFA Manager 06" />
	<game id="4726" name="Star Wars Empire at War" />
	<game id="4727" name="Metal Gear Solid2 Substance" />
	<game id="4728" name="KumaWar" />
	<game id="4729" name="Heroes of Might and Magic III" />
	<game id="4730" name="Heroes of Might and Magic III Armageddon's Blade" />
	<game id="4731" name="Rakion Chaos Force" />
	<game id="4732" name="Midtown Madness" />
	<game id="4733" name="Midtown Madness 2" />
	<game id="4734" name="Monster Truck Madness 2" />
	<game id="4735" name="Motocross Madness 2" />
	<game id="4736" name="Rainbow Six Lockdown Demo" />
	<game id="4737" name="Star Wars Empire at War Demo" />
	<game id="4738" name="Final Fantasy VII" />
	<game id="4739" name="Final Fantasy VIII" />
	<game id="4740" name="Battle for Middle-earth II Beta" />
	<game id="4741" name="Heroes of Might and Magic V Beta" />
	<game id="4742" name="MX vs ATV Unleashed Demo" />
	<game id="4743" name="FSW Ten Hammers" />
	<game id="4744" name="MX vs ATV Unleashed" />
	<game id="4745" name="Freecell" />
	<game id="4746" name="Hearts" />
	<game id="4747" name="Pinball" />
	<game id="4748" name="Devastation" />
	<game id="4749" name="Heroes of Might and Magic IV" />
	<game id="4750" name="Rainbow Six Lockdown" />
	<game id="4751" name="Marc Ecko's Getting Up - Contents Under Pressure" />
	<game id="4752" name="GT Legends" />
	<game id="4753" name="Trackmania Nations" />
	<game id="4754" name="C&amp;C Red Alert" />
	<game id="4755" name="Command &amp; Conquer" />
	<game id="4756" name="SpaceCowboy" />
	<game id="4757" name="Battle for Middle-earth II" />
	<game id="4758" name="Toca Race Driver 3" />
	<game id="4759" name="RF Online" />
	<game id="4760" name="Cabela's Big Game Hunter 2006" />
	<game id="4761" name="Deer Hunter 2003" />
	<game id="4762" name="Deer Hunter 2004" />
	<game id="4763" name="Deer Hunter 2005" />
	<game id="4764" name="Myst" />
	<game id="4765" name="Riven" />
	<game id="4766" name="Myst III Exile" />
	<game id="4767" name="Myst IV Revelation" />
	<game id="4768" name="Myst V End of Ages" />
	<game id="4769" name="Auto Assault" />
	<game id="4770" name="Dungeons &amp; Dragons Online - Stormreach" />
	<game id="4771" name="The Sims 2 Open for Business" />
	<game id="4772" name="SWAT 4 - The Stetchkov Syndicate" />
	<game id="4773" name="NCAA Championship Run 2006" />
	<game id="4774" name="The Elder Scrolls IV: Oblivion" />
	<game id="4775" name="Dark Age of Camelot - Darkness Rising" />
	<game id="4776" name="The Godfather" />
	<game id="4777" name="Red Orchestra Ostfront 41-45 (Steam)" />
	<game id="4778" name="Galactic Civilizations II" />
	<game id="4779" name="Galactic Civilizations" />
	<game id="4780" name="Galactic Civilizations - The Altarian Prophecy" />
	<game id="4781" name="18 Wheels of Steel Across America" />
	<game id="4782" name="Sin (Steam)" />
	<game id="4783" name="Sin Multiplayer (Steam)" />
	<game id="4784" name="SpellForce2 - Shadow Wars" />
	<game id="4785" name="Commandos Strikeforce" />
	<game id="4786" name="Tomb Raider - Legend" />
	<game id="4787" name="The Sims 2 Family Fun Stuff" />
	<game id="5439" name="Sword of the Stars Collectors' Edition" />
	<game id="4788" name="Sword of the Stars" />
	<game id="4789" name="True Crime - New York City" />
	<game id="4790" name="Shattered Galaxy" />
	<game id="4791" name="WWII Online" />
	<game id="4792" name="Blazing Angels" />
	<game id="4793" name="Heroes of Might and Magic V Demo" />
	<game id="4794" name="Titan Quest Demo" />
	<game id="4795" name="Condemned - Criminal Origins" />
	<game id="4796" name="2006 FIFA World Cup" />
	<game id="4797" name="Dangerous Waters" />
	<game id="4798" name="Dune 2000" />
	<game id="4799" name="Emperor - Battle for Dune" />
	<game id="4800" name="Ghost Recon Advanced Warfighter Demo" />
	<game id="4801" name="Sid Meier's Alpha Centauri" />
	<game id="4802" name="Winning Eleven 9" />
	<game id="4803" name="Ghost Recon Advanced Warfighter" />
	<game id="4804" name="Call of Cthulhu DCoTE" />
	<game id="4805" name="The Settlers IV" />
	<game id="4806" name="Hearts of Iron II Doomsday" />
	<game id="4807" name="UberSoldier" />
	<game id="4808" name="Dungeon Keeper 2" />
	<game id="4809" name="Tycoon City - New York" />
	<game id="4810" name="Crashday" />
	<game id="4811" name="Titan Quest" />
	<game id="4812" name="Tony Hawk's American Wasteland" />
	<game id="4813" name="Rise of Legends" />
	<game id="4814" name="Sin Episodes - Emergence" />
	<game id="4815" name="Heroes of Might and Magic V" />
	<game id="4816" name="City of Heroes Test Server" />
	<game id="4817" name="City of Villains Test Server" />
	<game id="4818" name="Dreamfall" />
	<game id="4819" name="DawnOfMen" />
	<game id="4820" name="GameTap" />
	<game id="4821" name="Hitman Blood Money" />
	<game id="4822" name="Half-Life 2: Episode One" />
	<game id="4823" name="Black &amp; White 2 Battle of the Gods" />
	<game id="4824" name="The Longest Journey" />
	<game id="4825" name="Shadowgrounds" />
	<game id="4826" name="The Da Vinci Code" />
	<game id="4827" name="Star Trek Armada II" />
	<game id="4828" name="Star Trek Away Team" />
	<game id="4829" name="Hidden: Source" />
	<game id="4830" name="Goldeneye: Source" />
	<game id="4831" name="Kreedz Climbing" />
	<game id="4832" name="Empires" />
	<game id="4833" name="Rogue Squadron" />
	<game id="4834" name="Star Wars Starfighter" />
	<game id="4835" name="Stacked" />
	<game id="4836" name="Asheron's Call" />
	<game id="4837" name="The Movies Stunts &amp; Effects" />
	<game id="4838" name="SimCity 3000" />
	<game id="4840" name="Game Tycoon" />
	<game id="4841" name="Total Overdose" />
	<game id="4842" name="Rush For Berlin" />
	<game id="4843" name="Xpand Rally" />
	<game id="4844" name="Locomotion" />
	<game id="4845" name="Dungeon Lords" />
	<game id="4846" name="Trainz Railroad Simulator 2006" />
	<game id="4847" name="Freedom Fighters" />
	<game id="4848" name="Prey Demo" />
	<game id="4849" name="Onimusha 3" />
	<game id="4850" name="Warsow" />
	<game id="4851" name="Albatross18" />
	<game id="4852" name="Sprint Cars: Road to Knoxville" />
	<game id="4853" name="Hitman - Codename 47" />
	<game id="4854" name="The Suffering Ties That Bind" />
	<game id="4855" name="Rise &amp; Fall" />
	<game id="4856" name="City Life" />
	<game id="4857" name="Rogue Trooper" />
	<game id="4858" name="Prey" />
	<game id="4859" name="NFL Head Coach" />
	<game id="4860" name="Act of War - High Treason" />
	<game id="4861" name="The Ship" />
	<game id="4862" name="X-Wing Alliance" />
	<game id="4863" name="Hero Online" />
	<game id="4864" name="Land of the Dead" />
	<game id="4865" name="Sword of the Stars Demo" />
	<game id="4866" name="Civilization IV - Warlords" />
	<game id="4867" name="CivCity Rome" />
	<game id="4868" name="OutRun2006 Coast 2 Coast" />
	<game id="4869" name="Glory of the Roman Empire" />
	<game id="4870" name="Sacrifice" />
	<game id="4871" name="MechWarrior 3" />
	<game id="4872" name="Dawn of War Dark Crusade" />
	<game id="4873" name="MechWarrior 4 Black Knight" />
	<game id="4874" name="Dungeon Siege II Broken World" />
	<game id="4875" name="Flatout 2" />
	<game id="4876" name="Untold Legends: Dark Kingdom" />
	<game id="4877" name="Hellgate: London" />
	<game id="4878" name="Company of Heroes Multiplayer Beta" />
	<game id="4879" name="FEAR Multiplayer" />
	<game id="4880" name="Battlefield 2142" />
	<game id="4881" name="Monopoly Tycoon" />
	<game id="4882" name="Madden NFL 07" />
	<game id="4883" name="Company of Heroes Single Player Demo" />
	<game id="4884" name="Dawn of War Dark Crusade Demo" />
	<game id="5143" name="Company of Heroes: Opposing Fronts" />
	<game id="4885" name="Company of Heroes" />
	<game id="4886" name="Lego Star Wars II" />
	<game id="4887" name="Mall Tycoon" />
	<game id="4888" name="Mall Tycoon 2" />
	<game id="4889" name="Mall Tycoon 3" />
	<game id="4890" name="School Tycoon" />
	<game id="4891" name="Airport Tycoon" />
	<game id="4892" name="Prison Tycoon 2" />
	<game id="4893" name="First Battalion" />
	<game id="4894" name="Faces of War" />
	<game id="4895" name="Patriots: A Nation Under Fire" />
	<game id="4896" name="Caesar 4 Demo" />
	<game id="4897" name="Dark Messiah Multiplayer Open Beta" />
	<game id="4898" name="FEAR Extraction Point SP Demo" />
	<game id="4899" name="Mage Knight Apocalypse" />
	<game id="4900" name="Caesar 4" />
	<game id="4901" name="NBA Live 07" />
	<game id="4902" name="NHL 07" />
	<game id="4903" name="Just Cause" />
	<game id="4904" name="The Sims 2 Glamour Life Stuff" />
	<game id="4905" name="FIFA 07" />
	<game id="4906" name="Disciples 2 - Gallean's Return" />
	<game id="4907" name="Disciples 2 - Rise of the Elves" />
	<game id="4908" name="Joint Task Force" />
	<game id="4909" name="Battlefield 2142 Demo" />
	<game id="4910" name="GTR 2" />
	<game id="4911" name="Scarface" />
	<game id="4912" name="Archlord" />
	<game id="4913" name="Medieval II Total War Demo SE" />
	<game id="4914" name="War Front - Turning Point" />
	<game id="4915" name="Gothic III" />
	<game id="4916" name="Tiger Woods PGA Tour 07" />
	<game id="4917" name="El Matador" />
	<game id="4918" name="Paraworld" />
	<game id="4919" name="Frets on Fire" />
	<game id="4920" name="Defcon" />
	<game id="4921" name="Championship Manager 2006" />
	<game id="4922" name="Age of Empires III: The WarChiefs" />
	<game id="4923" name="Microsoft Flight Simulator X" />
	<game id="4924" name="BZFlag" />
	<game id="4925" name="The Sims 2 Pets" />
	<game id="4926" name="Sid Meier's Railroads" />
	<game id="4927" name="The Guild 2" />
	<game id="4928" name="Neocron 2" />
	<game id="4929" name="Devil May Cry 3 Special Edition" />
	<game id="4930" name="Space Empires IV Deluxe" />
	<game id="4931" name="Space Empires V" />
	<game id="4932" name="Shot Online" />
	<game id="4934" name="Star Wars Empire at War Forces of Corruption" />
	<game id="4935" name="Phantasy Star Universe Online" />
	<game id="4936" name="Dark Messiah Multiplayer" />
	<game id="4937" name="Dark Messiah Single Player" />
	<game id="4938" name="FEAR Extraction Point" />
	<game id="4939" name="Stronghold Legends" />
	<game id="4940" name="Perimeter" />
	<game id="4941" name="Perimeter Emperor's Testament" />
	<game id="4942" name="Neverwinter Nights 2" />
	<game id="4943" name="Need for Speed Carbon" />
	<game id="4944" name="Marvel Ultimate Alliance" />
	<game id="4945" name="Need for Speed Carbon Demo" />
	<game id="4946" name="Pro Evolution Soccer 6" />
	<game id="4947" name="Football Manager 2007" />
	<game id="4948" name="Championship Manager 2007" />
	<game id="4949" name="Splinter Cell Double Agent Single Player" />
	<game id="4950" name="Splinter Cell Double Agent Multiplayer" />
	<game id="4951" name="SkillGround.com" />
	<game id="4952" name="1701 A.D" />
	<game id="4953" name="Medieval II Total War" />
	<game id="4954" name="Panzer Command" />
	<game id="4955" name="Warhammer Mark of Chaos" />
	<game id="4956" name="Heroes of Might and Magic V - Hammers of Fate" />
	<game id="4957" name="Falcon 4.0 Allied Force" />
	<game id="4958" name="Eragon" />
	<game id="4959" name="The Settlers II - 10th Anniversary" />
	<game id="4960" name="Reservoir Dogs" />
	<game id="4961" name="Digital Paint: Paintball 2" />
	<game id="4962" name="The Lord of the Rings, The Rise of the Witch-king" />
	<game id="4963" name="Rappelz Epic3" />
	<game id="4964" name="Star Trek Legacy" />
	<game id="4965" name="Tom Clancy's Rainbow Six Vegas" />
	<game id="4966" name="ijji GunZ" />
	<game id="4967" name="Vanguard - Saga of Heroes" />
	<game id="4968" name="CABAL Online (Europe)" />
	<game id="4969" name="Trickster Revolution" />
	<game id="4970" name="Pirates of the Caribbean" />
	<game id="4971" name="Dark Age of Camelot - Labyrinth of the Minotaur" />
	<game id="4972" name="Battlefield 1942 Multiplayer Demo" />
	<game id="4973" name="Battlefield 1942 Singleplayer Demo" />
	<game id="4974" name="Battlefield 1942 Secret Weapons of WWII Demo" />
	<game id="4975" name="Titan Quest Immortal Throne" />
	<game id="4976" name="Supreme Commander" />
	<game id="4977" name="Goonzu Online" />
	<game id="4978" name="25 to Life" />
	<game id="4979" name="Battlestations Midway" />
	<game id="4980" name="Bad Day LA" />
	<game id="4981" name="Let's Ride! - Silver Buckle Stables" />
	<game id="4982" name="James Bond 007 Nightfire" />
	<game id="4983" name="Mythos" />
	<game id="4984" name="Soldier Front" />
	<game id="4985" name="The Sims Life Stories" />
	<game id="4986" name="Maelstrom" />
	<game id="4987" name="The Curse of Monkey Island" />
	<game id="4988" name="Escape from Monkey Island" />
	<game id="4989" name="TMNT Demo" />
	<game id="4990" name="Warhammer Mark of Chaos MP Demo" />
	<game id="4991" name="Trackmania United Forever" />
	<game id="4992" name="Absolute Poker.com" />
	<game id="4993" name="Doyles Room.com" />
	<game id="4994" name="Everest Poker.com" />
	<game id="4995" name="Full Tilt Poker.com" />
	<game id="4996" name="Paradise Poker.com" />
	<game id="4997" name="PKR.com" />
	<game id="4998" name="Ultimate Bet.com" />
	<game id="4999" name="WPTOnline.com" />
	<game id="5000" name="Command &amp; Conquer 3 Tiberium Wars Demo" />
	<game id="5001" name="Jade Empire" />
	<game id="5002" name="The Sims 2 Seasons" />
	<game id="5003" name="Space Rangers 2" />
	<game id="5004" name="Railroad Tycoon II" />
	<game id="5005" name="Railroad Tycoon II Platinum" />
	<game id="5006" name="Sonic Riders" />
	<game id="5007" name="Sonic Heroes" />
	<game id="5008" name="Source SDK Base" />
	<game id="5009" name="S.T.A.L.K.E.R. - Shadow of Chernobyl" />
	<game id="5010" name="TMNT" />
	<game id="5011" name="Silent Hunter Wolves of the Pacific" />
	<game id="5012" name="Silverfall" />
	<game id="5013" name="Command &amp; Conquer 3 Tiberium Wars" />
	<game id="5014" name="Test Drive Unlimited" />
	<game id="5015" name="18 Wheels of Steel Haulin" />
	<game id="5016" name="rFactor" />
	<game id="5017" name="Half-Life Deathmatch: Source" />
	<game id="5018" name="Baseball Mogul 2008" />
	<game id="5019" name="Genesis Rising" />
	<game id="5020" name="Call of Juarez" />
	<game id="5021" name="The Lord of the Rings Online" />
	<game id="5022" name="The Sims 2 Celebration! Stuff" />
	<game id="5023" name="ArmA" />
	<game id="5024" name="Tortuga - Two Treasures" />
	<game id="5025" name="Europa Universalis III" />
	<game id="5026" name="Winning Eleven Pro Evolution Soccer 2007" />
	<game id="5027" name="Race - The WTCC Game" />
	<game id="5028" name="Resident Evil 4" />
	<game id="5029" name="Ancient Wars - Sparta" />
	<game id="5030" name="Spider-Man 3" />
	<game id="5031" name="Frontline - Fields of Thunder" />
	<game id="5032" name="Broken Sword - The Angel of Death" />
	<game id="5033" name="Cricket 07" />
	<game id="5034" name="Chess Titans" />
	<game id="5035" name="Inkball" />
	<game id="5036" name="Mahjong Titans" />
	<game id="5037" name="Purble Place" />
	<game id="5038" name="Hold 'Em" />
	<game id="5039" name="Brian Lara International Cricket 2007" />
	<game id="5040" name="LMA Manager 2007" />
	<game id="5041" name="UEFA Champions League 2006-2007" />
	<game id="5042" name="FIFA Manager 07" />
	<game id="5043" name="Virtua Tennis 3" />
	<game id="5044" name="Boiling Point" />
	<game id="5045" name="Cellfactor Revolution" />
	<game id="5046" name="Infernal" />
	<game id="5047" name="Crazy Taxi" />
	<game id="5048" name="Last Chaos USA" />
	<game id="5049" name="The Sims 2 Deluxe" />
	<game id="5050" name="Harry Potter and the Prisoner of Azkaban" />
	<game id="5051" name="Broken Sword - The Sleeping Dragon" />
	<game id="5052" name="Syberia" />
	<game id="5053" name="Syberia2" />
	<game id="5054" name="Voyage Century Online" />
	<game id="5055" name="Sauerbraten" />
	<game id="5056" name="Dogz 4" />
	<game id="5057" name="Freeciv - beta" />
	<game id="5058" name="Tibia" />
	<game id="5059" name="UFO - Extraterrestrial" />
	<game id="5060" name="Pirates of the Caribbean - At World's End" />
	<game id="5061" name="Halo 2" />
	<game id="5062" name="Attack on Pearl Harbor" />
	<game id="5063" name="Red Alert: A Path Beyond" />
	<game id="5064" name="Entropia Universe" />
	<game id="5065" name="World of Padman" />
	<game id="5066" name="Populous - The Beginning" />
	<game id="5067" name="Populous - The Beginning - Undiscovered Worlds" />
	<game id="5068" name="Tomb Raider - Anniversary" />
	<game id="5069" name="Baldur's Gate II" />
	<game id="5070" name="Birth of America" />
	<game id="5071" name="Neverwinter Nights 2 AMD 64 Version" />
	<game id="5073" name="Harry Potter and the Sorcerer's Stone" />
	<game id="5074" name="Harry Potter - Quidditch World Cup" />
	<game id="5075" name="Sword of the Stars - Born of Blood" />
	<game id="5076" name="Audition" />
	<game id="5077" name="DiRT" />
	<game id="5078" name="Scions of fate" />
	<game id="5079" name="Tremulous" />
	<game id="5080" name="Enemy Territory: QUAKE Wars" />
	<game id="5081" name="Catz (Deprecated)" />
	<game id="5082" name="Dogz (Deprecated)" />
	<game id="5083" name="The Sims 2 H&amp;M Fashion Stuff" />
	<game id="5084" name="The Sims Pet Stories" />
	<game id="5085" name="Overlord" />
	<game id="5086" name="Monster Madness - Battle for Suburbia" />
	<game id="5087" name="Lost Planet Extreme Condition" />
	<game id="5088" name="Harry Potter and the Order of the Phoenix" />
	<game id="5089" name="D.i.R.T. - Origin of the Species" />
	<game id="5090" name="Hospital Tycoon" />
	<game id="5091" name="Mount &amp; Blade" />
	<game id="5092" name="World in Conflict - BETA" />
	<game id="5093" name="Mysteries of the Sith" />
	<game id="5094" name="Sword of the New World" />
	<game id="5095" name="Transformers - The Game" />
	<game id="5096" name="Insurgency - Modern Infantry Combat" />
	<game id="5097" name="Ghost Recon Advanced Warfighter 2" />
	<game id="5098" name="Kwonho" />
	<game id="5099" name="Penumbra Overture Ep1" />
	<game id="5100" name="Taito Legends 2" />
	<game id="5101" name="Dungeon Runners" />
	<game id="5102" name="3D Model Trains" />
	<game id="5103" name="Civilization IV - Beyond the Sword" />
	<game id="5104" name="Baseball Mogul 2007" />
	<game id="5105" name="MicroMachines V4" />
	<game id="5106" name="Catz" />
	<game id="5107" name="Dogz" />
	<game id="5108" name="Rappelz Epic5" />
	<game id="5109" name="Metin 2" />
	<game id="5110" name="Tabula Rasa" />
	<game id="5111" name="Warhammer Online Beta" />
	<game id="5112" name="Avencast" />
	<game id="5113" name="2Moons" />
	<game id="5114" name="DANCE! Online" />
	<game id="5115" name="Madden NFL 08" />
	<game id="5116" name="Shadowrun" />
	<game id="5117" name="FreeStyle Street Basketball" />
	<game id="5118" name="BioShock Demo" />
	<game id="5119" name="BioShock" />
	<game id="5120" name="Medal of Honor: Airborne" />
	<game id="5121" name="Medal of Honor: Airborne - Demo" />
	<game id="5122" name="World in Conflict - DEMO" />
	<game id="5123" name="Two Worlds Demo" />
	<game id="5124" name="Two Worlds" />
	<game id="5125" name="Medieval II Total War: Kingdoms" />
	<game id="5126" name="Tiger Woods PGA Tour 08" />
	<game id="5127" name="Desperate Housewives" />
	<game id="5128" name="Urban Terror" />
	<game id="5129" name="Pet Vet 3D Animal Hospital" />
	<game id="5130" name="The Sims 2 Bon Voyage" />
	<game id="5131" name="Enemy Territory: QUAKE Wars Demo" />
	<game id="5132" name="World in Conflict Single Player" />
	<game id="5133" name="World in Conflict Multiplayer" />
	<game id="5134" name="Team Fortress 2" />
	<game id="5135" name="Peggle Extreme" />
	<game id="5136" name="Mayhem Intergalactic" />
	<game id="5137" name="Mayhem Intergalactic Demo" />
	<game id="5138" name="Crysis MP Beta" />
	<game id="5139" name="Frontlines: Fuel of War Beta" />
	<game id="5140" name="Drift City" />
	<game id="5141" name="John Woo Presents Stranglehold" />
	<game id="5142" name="NHL 08" />
	<game id="5144" name="Blazing Angels 2: Secret Missions of WWII" />
	<game id="5145" name="Big Mutha Truckers 2" />
	<game id="5146" name="Fortress Forever" />
	<game id="5147" name="The Settlers: Rise of an Empire" />
	<game id="5148" name="Babo Violent 2" />
	<game id="5149" name="CodeNameD: BlueShift" />
	<game id="5150" name="KartRider" />
	<game id="5151" name="CSI: Hard Evidence" />
	<game id="5152" name="UFO: Afterlight" />
	<game id="5153" name="Portal" />
	<game id="5154" name="Half-Life 2: Episode Two" />
	<game id="5155" name="FIFA 08" />
	<game id="5156" name="Loki" />
	<game id="5157" name="Call of Duty 4: Modern Warfare Demo" />
	<game id="5158" name="Unreal Tournament 3 Demo" />
	<game id="5159" name="Project Torque" />
	<game id="5160" name="Sid Meier's SimGolf" />
	<game id="5161" name="Legends" />
	<game id="5162" name="Brain Spa" />
	<game id="5163" name="Heroes of Might and Magic V: Tribes of the East" />
	<game id="5164" name="Fury" />
	<game id="5165" name="Hellgate: London Demo" />
	<game id="5166" name="City Life Deluxe" />
	<game id="5167" name="Galactic Civilizations II: Dark Avatar" />
	<game id="5168" name="CSPromod Beta" />
	<game id="5169" name="8BallClub" />
	<game id="5170" name="Worldwide Soccer Manager 2008" />
	<game id="5171" name="Football Manager 2008" />
	<game id="5172" name="Clive Barker's Jericho" />
	<game id="5173" name="Age of Empires III: The Asian Dynasties" />
	<game id="5174" name="Dynasty Warriors 4 Hyper" />
	<game id="5175" name="Crysis SP Demo" />
	<game id="5176" name="Painkiller: Overdose" />
	<game id="5177" name="SunAge" />
	<game id="5178" name="Luminary: Rise of Goonzu" />
	<game id="5179" name="The Witcher" />
	<game id="5180" name="TimeShift" />
	<game id="5181" name="Happy Feet" />
	<game id="5182" name="NBA Live 08" />
	<game id="5183" name="Taito Legends" />
	<game id="5184" name="Perfect World" />
	<game id="5185" name="Call of Duty 4: Modern Warfare Single Player" />
	<game id="5186" name="Call of Duty 4: Modern Warfare Multiplayer" />
	<game id="5187" name="Supreme Commander: Forged Alliance" />
	<game id="5188" name="Empire Earth III" />
	<game id="5189" name="FEAR Perseus Mandate" />
	<game id="5190" name="Gears of War" />
	<game id="5191" name="Dawn of War: Soulstorm" />
	<game id="5192" name="Pro Evolution Soccer 2008" />
	<game id="5193" name="Chessmaster Grandmaster Edition" />
	<game id="5194" name="Crysis" />
	<game id="5195" name="Dawn of Magic" />
	<game id="5196" name="You Are Empty" />
	<game id="5197" name="Guitar Hero III" />
	<game id="5198" name="Need for Speed ProStreet" />
	<game id="5199" name="Beowulf" />
	<game id="5200" name="Simcity Societies" />
	<game id="5201" name="Pinball Wizards: Balls of Steel Demo" />
	<game id="5202" name="Spider-Man: Friend or Foe" />
	<game id="5203" name="BlackSite: Area 51" />
	<game id="5204" name="Soldier of Fortune: Payback" />
	<game id="5205" name="Viva Pinata" />
	<game id="5206" name="WolfTeam" />
	<game id="5207" name="Fantasy Wars" />
	<game id="5208" name="Unreal Tournament 3" />
	<game id="5209" name="Avencast: Rise of The Mage" />
	<game id="5210" name="Next Life" />
	<game id="5211" name="Risk" />
	<game id="5212" name="Instinct" />
	<game id="5213" name="Gothic" />
	<game id="5214" name="Kane and Lynch: Dead Men" />
	<game id="5215" name="Exteel" />
	<game id="5216" name="The Office" />
	<game id="5217" name="Escape From Paradise City" />
	<game id="5218" name="Catz 2" />
	<game id="5219" name="Dogz 2" />
	<game id="5220" name="Horsez 2" />
	<game id="5221" name="BMW M3 Challenge" />
	<game id="5222" name="Dofus" />
	<game id="5223" name="Quake" />
	<game id="5224" name="SEGA Rally Revo" />
	<game id="5225" name="Planeshift" />
	<game id="5226" name="Alpha Prime" />
	<game id="5227" name="Ghost in the Sheet" />
	<game id="5228" name="Ascension" />
	<game id="5229" name="Speedball 2 - Tournament" />
	<game id="5230" name="Alvin and the Chipmunks" />
	<game id="5231" name="Fiesta" />
	<game id="5232" name="Universe At War: Earth Assault" />
	<game id="5233" name="RACE 07" />
	<game id="5234" name="Battle for the Pacific" />
	<game id="5235" name="Warmonger - Operation: Downtown Destruction" />
	<game id="5236" name="Arcanum: Of Steamworks and Magick Obscura" />
	<game id="5237" name="Shogun: Total War" />
	<game id="5238" name="Shaiya" />
	<game id="5239" name="The Golden Compass" />
	<game id="5240" name="Dream Of Mirror Online" />
	<game id="5241" name="PKRCasino" />
	<game id="5242" name="Twelve Sky" />
	<game id="5243" name="Regnum Online" />
	<game id="5244" name="Beyond Divinity" />
	<game id="5245" name="Geometry Wars: Retro Evolved" />
	<game id="5246" name="Kane and Lynch: Dead Men Demo" />
	<game id="5247" name="Hard To Be a God Demo" />
	<game id="5248" name="Indiana Jones and the Emperors Tomb" />
	<game id="5249" name="Grand Theft Auto" />
	<game id="5250" name="Peggle Deluxe" />
	<game id="5251" name="Juiced 2: Hot Import Nights" />
	<game id="5252" name="Phantasy Star Universe: Ambition of the Illuminus" />
	<game id="5253" name="Pirates of the Burning Sea" />
	<game id="5254" name="Battlestar Galactica" />
	<game id="5255" name="Puzzle Quest: Challenge of the Warlords" />
	<game id="5256" name="Dawn of War: Soulstorm Demo" />
	<game id="5257" name="Teewars" />
	<game id="5258" name="Metal Gear Solid" />
	<game id="5259" name="Indiana Jones and the Infernal Machine" />
	<game id="5260" name="Divine Divinity" />
	<game id="5261" name="Rising Eagle" />
	<game id="5262" name="Hard Truck: 18 Wheels of Steel" />
	<game id="5263" name="Stranded II" />
	<game id="5264" name="Pirates of the Caribbean Online" />
	<game id="5265" name="Wild Metal Country" />
	<game id="5266" name="GGPO.net" />
	<game id="5267" name="Jewel Quest" />
	<game id="5268" name="9Dragons" />
	<game id="5269" name="Feeding Frenzy 2 Deluxe" />
	<game id="5270" name="Bejeweled Deluxe" />
	<game id="5271" name="Bejeweled 2 Deluxe" />
	<game id="5272" name="Chuzzle Deluxe" />
	<game id="5273" name="Insaniquarium Deluxe" />
	<game id="5274" name="AstroPop Deluxe" />
	<game id="5275" name="Iggle Pop Deluxe" />
	<game id="5276" name="Zuma Deluxe" />
	<game id="5277" name="Dynomite Deluxe" />
	<game id="5278" name="Big Money Deluxe" />
	<game id="5279" name="Heavy Weapon Deluxe" />
	<game id="5280" name="Pizza Frenzy Deluxe" />
	<game id="5281" name="Hammer Heads Deluxe" />
	<game id="5282" name="Typer Shark Deluxe" />
	<game id="5283" name="Rail Simulator" />
	<game id="5284" name="Bookworm Deluxe" />
	<game id="5285" name="Bookworm Adventures Deluxe" />
	<game id="5286" name="Sins of a Solar Empire" />
	<game id="5287" name="The Sims Castaway Stories" />
	<game id="5288" name="Thrillville: Off the Rails" />
	<game id="5289" name="Secret of the Solstice" />
	<game id="5290" name="CABAL Online: The Revolution of Action" />
	<game id="5291" name="Holic" />
	<game id="5292" name="Racer Beta" />
	<game id="5293" name="FIFA Manager 08" />
	<game id="5294" name="The Spiderwick Chronicles" />
	<game id="5295" name="Conflict: Denied Ops" />
	<game id="5296" name="Harley-Davidson Race to the Rally" />
	<game id="5297" name="Manga Fighter" />
	<game id="5298" name="Audiosurf" />
	<game id="5299" name="Impossible Creatures" />
	<game id="5300" name="Resident Evil 3: Nemesis" />
	<game id="5301" name="Theme Hospital" />
	<game id="5302" name="AirRivals" />
	<game id="5303" name="RuneScape" />
	<game id="5304" name="Penumbra: Black Plague" />
	<game id="5305" name="Hello Kitty Cutie World" />
	<game id="5306" name="Beyond Good &amp; Evil" />
	<game id="5307" name="The Club" />
	<game id="5308" name="Europa 1400: The Guild (Gold)" />
	<game id="5309" name="Red Stone" />
	<game id="5310" name="Frontlines: Fuel of War" />
	<game id="5311" name="Grand Chase (Asia)" />
	<game id="5312" name="Grand Chase" />
	<game id="5313" name="The Sims 2 FreeTime" />
	<game id="5314" name="Turning Point: Fall of Liberty" />
	<game id="5315" name="Lost: Via Domus" />
	<game id="5316" name="Phun" />
	<game id="5317" name="SpaceForce Captains" />
	<game id="5318" name="NASCAR Racing 2002 Season" />
	<game id="5319" name="Darkeden" />
	<game id="5320" name="The Experiment" />
	<game id="5321" name="FairyLand" />
	<game id="5322" name="Fritz 8" />
	<game id="5323" name="Bots" />
	<game id="5324" name="Crusaders: Thy Kingdom Come" />
	<game id="5325" name="Crusaders: Thy Kingdom Come Multiplayer" />
	<game id="5326" name="Cal Ripken's Real Baseball" />
	<game id="5327" name="Pirates, Vikings and Knights II" />
	<game id="5328" name="Worms 2" />
	<game id="5329" name="Savage 2: A Tortured Soul" />
	<game id="5330" name="Phantasy Star Online: Blue Burst" />
	<game id="5331" name="Pirateville" />
	<game id="5332" name="Upshift StrikeRacer" />
	<game id="5333" name="Glest" />
	<game id="5334" name="WorldShift Beta" />
	<game id="5335" name="Seven Kingdoms: Conquest" />
	<game id="5336" name="Powerboat GT" />
	<game id="5337" name="Chessmaster 10th Edition" />
	<game id="5338" name="Red Baron Arcade" />
	<game id="5339" name="The Shield" />
	<game id="5340" name="Mind Quiz" />
	<game id="5341" name="Ricochet Infinity" />
	<game id="5342" name="Command &amp; Conquer 3: Kane's Wrath" />
	<game id="5343" name="Lost Empire: Immortals" />
	<game id="5344" name="Hard Truck 2" />
	<game id="5345" name="Lights Out" />
	<game id="5346" name="SWAT 3" />
	<game id="5347" name="The Sims Carnival: BumperBlast" />
	<game id="5348" name="The Sims Carnival: SnapCity" />
	<game id="5349" name="Toribash" />
	<game id="5350" name="Osu!" />
	<game id="5351" name="Pet Luv Spa and Resort Tycoon" />
	<game id="5352" name="Perfect Dark: Source" />
	<game id="5353" name="Trials 2: Second Edition" />
	<game id="5354" name="Synergy" />
	<game id="5355" name="Rohan: Blood Feud" />
	<game id="5356" name="Warriors Orochi" />
	<game id="5357" name="Alien Arena 2008" />
	<game id="5358" name="Ninja Reflex: Steamworks Edition" />
	<game id="5359" name="Lunia" />
	<game id="5360" name="Uplink" />
	<game id="5361" name="Slayers Online" />
	<game id="5362" name="Second Sight" />
	<game id="5363" name="Imperium Romanum" />
	<game id="5364" name="Yu-Gi-Oh! Online: Duel Evolution" />
	<game id="5365" name="Assassin's Creed" />
	<game id="5366" name="Terra: Battle for the Outlands" />
	<game id="5367" name="Darkstar One" />
	<game id="5368" name="OpenTTD" />
	<game id="5369" name="NosTale" />
	<game id="5370" name="Jagged Alliance 2 Gold" />
	<game id="5371" name="American McGee's Alice" />
	<game id="5372" name="Skulltag" />
	<game id="5373" name="Saga" />
	<game id="5374" name="Trackmania Nations Forever" />
	<game id="5375" name="Tom Clancy's Rainbow Six Vegas 2" />
	<game id="5376" name="The Sims 2 Kitchen &amp; Bath Interior Design Stuff" />
	<game id="5377" name="Kung Fu Panda Demo" />
	<game id="5378" name="Melty Blood: Act Cadenza" />
	<game id="5379" name="Seal Online USA" />
	<game id="5380" name="Magic Online III" />
	<game id="5381" name="Ultimate Doom" />
	<game id="5382" name="Master Levels of Doom" />
	<game id="5383" name="Final Doom" />
	<game id="5384" name="Doom 2" />
	<game id="5385" name="Cabela's Dangerous Hunts 2" />
	<game id="5386" name="Turok" />
	<game id="5387" name="Clive Barker's Undying" />
	<game id="5388" name="Lumines" />
	<game id="5389" name="Europa Universalis: Rome" />
	<game id="5390" name="Planescape: Torment" />
	<game id="5391" name="Dirty Dancing: The Video Game" />
	<game id="5392" name="Age of Conan: Hyborian Adventures" />
	<game id="5393" name="The House of the Dead 3" />
	<game id="5394" name="The House of the Dead 2" />
	<game id="5395" name="Iron Man" />
	<game id="5396" name="Sherlock Holmes: Nemesis" />
	<game id="5397" name="Galactic Civilizations II: Twilight of the Arnor" />
	<game id="5398" name="Imperialism II" />
	<game id="5399" name="Star Wars: Battle for Naboo" />
	<game id="5400" name="Grand Prix 4" />
	<game id="5401" name="Tomb Raider II" />
	<game id="5402" name="Commandos 3: Destination Berlin" />
	<game id="5403" name="Capitalism II" />
	<game id="5404" name="Tales of Pirates Online" />
	<game id="5405" name="Bet and Race" />
	<game id="5406" name="Commandos: Behind Enemy Lines" />
	<game id="5407" name="Magic The Gathering: Battlegrounds" />
	<game id="5408" name="Everyday Shooter" />
	<game id="5409" name="Graal Online" />
	<game id="5410" name="Heretic II" />
	<game id="5411" name="Conflict: Global Terror" />
	<game id="5412" name="Jack Keane" />
	<game id="5413" name="Shogo: Mobile Armor Division" />
	<game id="5414" name="Cossacks: The Art Of War" />
	<game id="5415" name="Requiem: Bloodymare" />
	<game id="5416" name="Hello Kitty Online" />
	<game id="5417" name="On the Rain-Slick Precipice of Darkness, Episode One" />
	<game id="5418" name="PseudoQuest" />
	<game id="5419" name="Mortimer Beckett and the Secrets of Spooky Manor" />
	<game id="5420" name="Silent Hunter II" />
	<game id="5421" name="Flanker 2.5" />
	<game id="5422" name="The Continuum" />
	<game id="5423" name="Great War Nations: The Spartans" />
	<game id="5424" name="Shadowgrounds Survivor" />
	<game id="5425" name="Mass Effect" />
	<game id="5426" name="Lost Planet: Extreme Condition Colonies Edition" />
	<game id="5427" name="G-Police" />
	<game id="5428" name="Heroes of Might and Magic III Complete" />
	<game id="5429" name="GRID Demo" />
	<game id="5430" name="Icewind Dale II" />
	<game id="5431" name="Day of Defeat: Source Beta" />
	<game id="5432" name="Spaceinvasion" />
	<game id="5433" name="ChaosCars" />
	<game id="5434" name="Gladiators II" />
	<game id="5435" name="Seafight" />
	<game id="5436" name="DarkOrbit" />
	<game id="5437" name="Lego Indiana Jones: The Original Adventures" />
	<game id="5438" name="GRID" />
	<game id="5440" name="Guilty Gear x2 Reload" />
	<game id="5441" name="Nitro Stunt Race Stage 1" />
	<game id="5442" name="MTV's Virtual World" />
	<game id="5443" name="Kung Fu Panda" />
	<game id="5444" name="Aliens versus Predator Gold Edition" />
	<game id="5445" name="Turok 2: Seeds of Evil Singleplayer" />
	<game id="5446" name="Turok 2: Seeds of Evil Multiplayer" />
	<game id="5447" name="Wonderland Online" />
	<game id="5448" name="Devil May Cry 4 Trial" />
	<game id="5449" name="Blokus World Tour" />
	<game id="5450" name="Star Sonata" />
	<game id="5451" name="Bullet Candy" />
	<game id="5452" name="Bus Driver" />
	<game id="5453" name="The Incredible Hulk" />
	<game id="5454" name="Stronghold Crusader Extreme" />
	<game id="5455" name="Marble Blast Gold" />
	<game id="5456" name="UEFA Euro 2008" />
	<game id="5458" name="Little Farm" />
	<game id="5459" name="SPORE Creature Creator" />
	<game id="5460" name="Psi-Ops: The Mindgate Conspiracy" />
	<game id="5461" name="Zu Online" />
	<game id="5462" name="Angels Online" />
	<game id="5463" name="Dreamlords: The Reawakening" />
	<game id="5464" name="Alien Shooter" />
	<game id="5465" name="WALL-E" />
	<game id="5466" name="Alone In The Dark" />
	<game id="5467" name="Crazy Machines 2" />
	<game id="5468" name="Out of the Park Baseball 9" />
	<game id="5469" name="The Sims 2 IKEA Home Stuff" />
	<game id="5470" name="World of Kung Fu" />
	<game id="5471" name="Making History: The Calm and The Storm" />
	<game id="5472" name="Freelanc3r" />
	<game id="5473" name="Genleo: The Land of Eratica" />
	<game id="5474" name="Seeds of Time Online" />
	<game id="5475" name="Oil Imperium" />
	<game id="5476" name="Combat Arms" />
	<game id="5477" name="Cardmaster Conflict" />
	<game id="5478" name="Freedom Force" />
	<game id="5479" name="Ultimate Pimpin'" />
	<game id="5480" name="Safari Photo Africa: Wild Earth" />
	<game id="5481" name="Supreme Ruler 2020" />
	<game id="5482" name="The Political Machine 2008" />
	<game id="5483" name="CS-Manager" />
	<game id="5484" name="Devil May Cry 4" />
	<game id="5485" name="Immune Attack" />
	<game id="5486" name="Carmageddon II: Carpocalypse Now!" />
	<game id="5487" name="Panzer Elite" />
	<game id="5488" name="Dark Colony" />
	<game id="5489" name="Enclave" />
	<game id="5490" name="Carmageddon TDR2000" />
	<game id="5491" name="Rayman Raving Rabbids" />
	<game id="5492" name="Rigs of Rods" />
	<game id="5493" name="7 Wonders of the Ancient World" />
	<game id="5494" name="Eternal Lands" />
	<game id="5495" name="The Golden Horde" />
	<game id="5496" name="Roogoo" />
	<game id="5497" name="Bomberman Online" />
	<game id="5498" name="Elements" />
	<game id="5499" name="The Wonderful End of the World" />
	<game id="5500" name="Halo Trial" />
	<game id="5501" name="Space Chimps" />
	<game id="5502" name="7 Wonders II" />
	<game id="5503" name="Sacred Gold" />
	<game id="5504" name="UniBall" />
	<game id="5505" name="Warrior Epic Closed Beta" />
	<game id="5506" name="World of Warcraft: Wrath of the Lich King Beta" />
	<game id="5507" name="Jutland Beta" />
	<game id="5508" name="IGI-2: Covert Strike" />
	<game id="5509" name="CQC: Close Quarter Combat" />
	<game id="5510" name="Q-World" />
	<game id="5511" name="Majesty Gold Edition" />
	<game id="5512" name="Majesty Gold Edition: The Northern Expansion" />
	<game id="5513" name="I.G.I.: I'm Going In" />
	<game id="5514" name="Transport Giant" />
	<game id="5515" name="Command &amp; Conquer: Red Alert 3 Beta" />
	<game id="5516" name="The Settlers III" />
	<game id="5517" name="Beijing 2008" />
	<game id="5518" name="Eschalon Book I" />
	<game id="5519" name="Sudden Strike 3: Arms for Victory" />
	<game id="5520" name="Project Powder Beta" />
	<game id="5521" name="Xiah Rebirth" />
	<game id="5522" name="Asda Story" />
	<game id="5523" name="Dream Pinball 3D" />
	<game id="5524" name="Sho Online" />
	<game id="5525" name="Space Siege" />
	<game id="5526" name="Shattered Suns" />
	<game id="5527" name="Harino" />
	<game id="5528" name="Pro Cycling Manager Season 2008" />
	<game id="5529" name="QPang" />
	<game id="5530" name="FATE: Undiscovered Realms" />
	<game id="5531" name="Dracula: Origin" />
	<game id="5532" name="The Sims 2 Apartment Life" />
	<game id="5533" name="Hunting Unlimited 2009" />
	<game id="5534" name="FlatOut: Ultimate Carnage" />
	<game id="5535" name="Battlefield Heroes Beta" />
	<game id="5536" name="4Story" />
	<game id="5537" name="Legend: Hand of God" />
	<game id="5538" name="Pi Story" />
	<game id="5539" name="Mercenaries 2: World in Flames" />
	<game id="5540" name="SPORE" />
	<game id="5541" name="Dracula 3: The Path of the Dragon" />
	<game id="5542" name="Demigod Beta" />
	<game id="5543" name="Rome: Total War: Alexander" />
	<game id="5544" name="Arca Sim Racing" />
	<game id="5545" name="Oddworld: Abe's Exoddus" />
	<game id="5546" name="Oddworld: Abe's Oddysee" />
	<game id="5547" name="FIFA 09 Demo" />
	<game id="5548" name="S.T.A.L.K.E.R.: Clear Sky" />
	<game id="5549" name="Warhammer Online: Age of Reckoning" />
	<game id="5550" name="Crysis Warhead" />
	<game id="5551" name="Crysis Wars" />
	<game id="5552" name="Romance of the Three Kingdoms XI" />
	<game id="5553" name="Pure" />
	<game id="5554" name="Source SDK Base: Orange Box" />
	<game id="5555" name="Lego Batman" />
	<game id="5556" name="Strong Bad's Cool Game for Attractive People Episode 1: Homestar Ruiner" />
	<game id="5557" name="Strong Bad's Cool Game for Attractive People Episode 2: Strong Badia the Free" />
	<game id="5558" name="Civilization IV: Colonization" />
	<game id="5559" name="Perfect World International" />
	<game id="5560" name="Multiwinia" />
	<game id="5561" name="City Life 2008" />
	<game id="5562" name="King's Bounty: The Legend" />
	<game id="5563" name="1701 A.D.: The Sunken Dragon" />
	<game id="5564" name="The Suffering" />
	<game id="5565" name="Russia's Army" />
	<game id="5566" name="Atlantica Online" />
</games>
